pyinpe/OGCapiFeatures.py
pyinpe/WFS.py
pyinpe/__init__.py
pyinpe/common.py
pyinpe/pyinpe.py
pyinpe/shapefile.py
pyinpe/__assets__/config.json
pyinpe/__assets__/geocode.csv
pyinpe/data/polygon.zip
pyinpe-0.0.27.dist-info/LICENSE
pyinpe-0.0.27.dist-info/METADATA
pyinpe-0.0.27.dist-info/WHEEL
pyinpe-0.0.27.dist-info/entry_points.txt
pyinpe-0.0.27.dist-info/top_level.txt
pyinpe-0.0.27.dist-info/RECORD
