Metadata-Version: 2.1
Name: pyinpe
Version: 0.0.27
Summary: A python package demo for environmental data
Author-email: Luiz Satolo <luizsatolo@hotmail.com>
License: MIT License
Project-URL: Homepage, https://github.com/luizsatolo/pyinpe
Keywords: pyinpe
Classifier: Intended Audience :: Developers
Classifier: License :: OSI Approved :: MIT License
Classifier: Natural Language :: English
Classifier: Programming Language :: Python :: 3.8
Classifier: Programming Language :: Python :: 3.9
Classifier: Programming Language :: Python :: 3.10
Classifier: Programming Language :: Python :: 3.11
Classifier: Programming Language :: Python :: 3.12
Requires-Python: >=3.8
License-File: LICENSE
Requires-Dist: geopandas
Requires-Dist: requests
Requires-Dist: shapely
Requires-Dist: pandas
Requires-Dist: numpy
Requires-Dist: pyogrio
Provides-Extra: all
Requires-Dist: pyinpe[extra] ; extra == 'all'
Provides-Extra: extra
Requires-Dist: pandas ; extra == 'extra'
